setup.py
Flask_LDAP.egg-info/PKG-INFO
Flask_LDAP.egg-info/SOURCES.txt
Flask_LDAP.egg-info/dependency_links.txt
Flask_LDAP.egg-info/not-zip-safe
Flask_LDAP.egg-info/requires.txt
Flask_LDAP.egg-info/top_level.txt
flask_ldap/__init__.py
flask_ldap/flask_ldap.py