Metadata-Version: 1.0
Name: Flask-LDAP
Version: 0.1.4
Summary: Flask extension for LDAP auth and profile user
Home-page: https://bitbucket.org/ellersseer/flask-ldap/
Author: Dmitry Zhiltsov
Author-email: dzhiltsov@me.com
License: BSD
Platform: any
Classifier: Environment :: Web Environment
Classifier: Intended Audience :: Developers
Classifier: License :: OSI Approved :: BSD License
Classifier: Operating System :: OS Independent
Classifier: Programming Language :: Python
Classifier: Topic :: Internet :: WWW/HTTP :: Dynamic Content
Classifier: Topic :: Software Development :: Libraries :: Python Modules
